{"stat.flyOneCm":496970,"stat.deaths":1,"stat.walkOneCm":40877,"stat.drop":1,"stat.swimOneCm":132,"stat.jump":80,"stat.playOneMinute":32735,"stat.climbOneCm":856,"stat.fallOneCm":7146,"achievement.openInventory":1,"stat.entityKilledBy.Wolf":1,"stat.killEntity.Chicken":1,"stat.leaveGame":1,"stat.damageTaken":400,"stat.damageDealt":160,"stat.timeSinceDeath":27835,"stat.mineBlock.minecraft.double_plant":1,"stat.mobKills":3,"achievement.exploreAllBiomes":{"value":0,"progress":["ForestHills","Birch Forest","Forest","River","Plains","Taiga","Extreme Hills","Swampland","TaigaHills"]},"stat.mineBlock.minecraft.tallgrass":2,"stat.diveOneCm":663}